[[["ititit","247482214","\/\/liveimg.afreecatv.com\/m\/247482214?510","보신대) 사탄 깨림이 힐링시켜주겠습니다","4133"],["daegalheo","247482617","\/\/liveimg.afreecatv.com\/m\/247482617?124"," 허유 vs 겐세이박 내 실력이 나도 궁금하다 스타 마이너즈","264"],["wjswpalssla1","247481820","\/\/liveimg.afreecatv.com\/m\/247481820?50","[라이트클럽 마이너즈] 스타 전제민 vs 허유형 3\/2","105"],["wodnr7872","247482670","\/\/liveimg.afreecatv.com\/m\/247482670?326","[겐세이박] 미션 받습니다 스타 팀플 빨무","75"],["rfvtgb778","247481422","\/\/liveimg.afreecatv.com\/m\/247481422?816","스타 이영웅 래더 알찬 강의방송^^ 시청자게임이후 피드백","65"],["mwhdgus","247479951","\/\/liveimg.afreecatv.com\/m\/247479951?261","[석사관] 스타 저그 윤진규 연블비 테란전 사람만들기","40"],["ynblbee","247482988","\/\/liveimg.afreecatv.com\/m\/247482988?892","[석사관] 징규쌤한테 테란전 교육받기 ㅇ_ㅇ!","30"],["snowssa","247468855","\/\/liveimg.afreecatv.com\/m\/247468855?845","[보신대] 녹.. 24시간 노방종 시작. \/  시흥스타정중만","24"],["luckycontrol","247457271","\/\/liveimg.afreecatv.com\/m\/247457271?794","[YB] 스타 고도준 하랑이 경기전에 옴니당 자고옴","8"],["askl021","247473702","\/\/liveimg.afreecatv.com\/m\/247473702?65","[석사관] 빡죠스 폐관수련 2500노방종 도전한다 미션 스폰 화녕","6"],["gjgj3274","247483494","\/\/liveimg.afreecatv.com\/m\/247483494?276","철기빵 스타 소룡이 게임시작 무따하지마세요.","2"],["busky3","247482454","\/\/liveimg.afreecatv.com\/m\/247482454?44","귀농4 야외 비빔쇼&amp;야스","460"],["dmsgkdn12","247482629","\/\/liveimg.afreecatv.com\/m\/247482629?197","하위 [신입N돌핀]","191"],["ggangsoony","247482666","\/\/liveimg.afreecatv.com\/m\/247482666?359","[MC크루] 데시벨측정 70db 실패시 국토100km걷기                            \/맨만숙흥구기날박엠씨크루","185"],["mochiya","247483135","\/\/liveimg.afreecatv.com\/m\/247483135?556","[오츠] =ㅅ= ","37"],["rrvv17","247445537","\/\/liveimg.afreecatv.com\/m\/247445537?807","킴성태 5시오성집합 자고오겠습니다 로나서버시즌2","5160"],["ititit","247482214","\/\/liveimg.afreecatv.com\/m\/247482214?806","보신대) 사탄 깨림이 힐링시켜주겠습니다","4133"],["didi5252","247469159","\/\/liveimg.afreecatv.com\/m\/247469159?735","지하킹김경제 쌩배부터 챌까지1일차.","1270"],["girlbbo","247477885","\/\/liveimg.afreecatv.com\/m\/247477885?940","걸뽀 [로나월드:시즌2]","584"],["watchfact","247471445","\/\/liveimg.afreecatv.com\/m\/247471445?486","와챠챠 - 길드완성 - [모이차마트] [로나월드 : 시즌2]","397"],["osim0408","247479851","\/\/liveimg.afreecatv.com\/m\/247479851?414","M202 초원 로리CK(1승) 현재 펀딩 1500개 ","363"],["daegalheo","247482617","\/\/liveimg.afreecatv.com\/m\/247482617?305"," 허유 vs 겐세이박 내 실력이 나도 궁금하다 스타 마이너즈","264"],["tjaudtn123","247481943","\/\/liveimg.afreecatv.com\/m\/247481943?528","서도일 로리ck 3승","127"],["kimseah94","247477087","\/\/liveimg.afreecatv.com\/m\/247477087?335","김세아 에메랄드 파다가 잠드는 방..[로나월드 : 시즌2]","114"],["wjswpalssla1","247481820","\/\/liveimg.afreecatv.com\/m\/247481820?590","[라이트클럽 마이너즈] 스타 전제민 vs 허유형 3\/2","105"],["wodnr7872","247482670","\/\/liveimg.afreecatv.com\/m\/247482670?833","[겐세이박] 미션 받습니다 스타 팀플 빨무","75"],["rfvtgb778","247481422","\/\/liveimg.afreecatv.com\/m\/247481422?842","스타 이영웅 래더 알찬 강의방송^^ 시청자게임이후 피드백","65"],["tladl5572","247483188","\/\/liveimg.afreecatv.com\/m\/247483188?170","d안녕하세용 아침요정 딤딤이 ^0^","64"],["yoomingseo","247482828","\/\/liveimg.afreecatv.com\/m\/247482828?567","[케크루] 유복실 앙녕","60"],["dlangusrnt","247481629","\/\/liveimg.afreecatv.com\/m\/247481629?266","무돌 배틀그라운드","54"],["mwhdgus","247479951","\/\/liveimg.afreecatv.com\/m\/247479951?405","[석사관] 스타 저그 윤진규 연블비 테란전 사람만들기","40"],["chw2440","247483106","\/\/liveimg.afreecatv.com\/m\/247483106?738","메이플 스카니아 제동빠 278 불독 정정당당재획","32"],["ynblbee","247482988","\/\/liveimg.afreecatv.com\/m\/247482988?922","[석사관] 징규쌤한테 테란전 교육받기 ㅇ_ㅇ!","30"],["ogm0905","247459639","\/\/liveimg.afreecatv.com\/m\/247459639?280","오뀨 12시에오겠습니다  그마마무리,, 380P 3만개 챌노방종","28"],["godnjs8482","247473737","\/\/liveimg.afreecatv.com\/m\/247473737?991","[BKG]24시간 노방종 공장 다과회 #킬내기공장 #BJ할배","25"],["snowssa","247468855","\/\/liveimg.afreecatv.com\/m\/247468855?861","[보신대] 녹.. 24시간 노방종 시작. \/  시흥스타정중만","24"],["jinhi1004","247482094","\/\/liveimg.afreecatv.com\/m\/247482094?954","로리ck 1승","18"],["e9dongsung","247482921","\/\/liveimg.afreecatv.com\/m\/247482921?632","여자 월드컵 대한민국:콜롬비아! 가자!!!","414"],["pop576","247481992","\/\/liveimg.afreecatv.com\/m\/247481992?367","[케크루] wwe raw 리코셰 챔피언 기원 1일차","67"]],{"캄성":1,"우끼끼즈":0,"JSA":0,"보신대":2,"DP":0,"라이트클럽":1,"흑카데미":0,"철기빵":2,"YB":2,"석사관":3,"나사":0,"늪지대":0}]