[[["arinbbidol","244013420","\/\/liveimg.afreecatv.com\/m\/244013420?186","기뉴다x유나땅 오버워치 ","1915"],["onlysibar","244012818","\/\/liveimg.afreecatv.com\/m\/244012818?13","스타 샤이니 테란 레더강의 맛집 보고S못찍으면 저그하세요?!","373"],["gjgj3274","244012898","\/\/liveimg.afreecatv.com\/m\/244012898?216","스타 래더 1등 이소룡 고민상담+래더강의 ","218"],["95yvely","244013711","\/\/liveimg.afreecatv.com\/m\/244013711?352","[바스포드] 일일카페 하고 허리 나갔음...","165"],["wodnr7872","244013130","\/\/liveimg.afreecatv.com\/m\/244013130?962","[겐세이박] with빵주둥,초난강 3:3 5연승미션 스타 팀플 빨무 아마대","115"],["wjddlf4695","244013831","\/\/liveimg.afreecatv.com\/m\/244013831?794","스타 마이너즈 짭호 H I ","64"],["rladuddo99","244013141","\/\/liveimg.afreecatv.com\/m\/244013141?801","[바스포드]스진남 구성훈 vs원선재 3\/2...","54"],["zealot0846","244013651","\/\/liveimg.afreecatv.com\/m\/244013651?868","스타 토스 원선재 토스의 정석방송 vs 잉어킹형님 3\/2","40"],["byebye22","244013891","\/\/liveimg.afreecatv.com\/m\/244013891?678","스타 애공이 하이하이 오랜만에 캠방똥","21"],["bts150","244013294","\/\/liveimg.afreecatv.com\/m\/244013294?718","NSU 스타 방태수 래더 저그","16"],["eeceec","244013119","\/\/liveimg.afreecatv.com\/m\/244013119?80","아마대  1800  래더시 3만개 현재 1660","15"],["bhy95","244013564","\/\/liveimg.afreecatv.com\/m\/244013564?245","아마대 스타 테란 배호연 잭티어 래더2800찍기 부지런1일차","10"],["dbrbals","244013689","\/\/liveimg.afreecatv.com\/m\/244013689?543","마이너즈 아마대 초난강 겐사장이랑 버스운행중~","9"],["guiltyinori","244013352","\/\/liveimg.afreecatv.com\/m\/244013352?287","[GOU]고대 0티어 테란 김기환 환협지 모드 on","9"],["qndnd12","244013703","\/\/liveimg.afreecatv.com\/m\/244013703?90","[AMA]아마대 스타 저그 알렌 vs 배호딱 잭티어 사냥꾼 출동","3"],["drumkyn","244012688","\/\/liveimg.afreecatv.com\/m\/244012688?29","주식왕용느★[인생찐찐찐막시즌]반대매매 당하니 오히려 좋네요 ...","3698"],["vlfvlf789","244013610","\/\/liveimg.afreecatv.com\/m\/244013610?493","수니그룹 하 벌써부터 니모컨 이간질 ㅈ대네","2908"],["ogm0905","244012494","\/\/liveimg.afreecatv.com\/m\/244012494?656","오뀨 천안  영하2도 따뜻하다..국토","1355"],["judy0848","244013124","\/\/liveimg.afreecatv.com\/m\/244013124?908","[수니그룹] 연기부 새로운 지원자 공개.. 그냥 싹 다 갈아 엎을까;","1121"],["busky3","244001992","\/\/liveimg.afreecatv.com\/m\/244001992?673","나는 자연인이다 리틀두레스트w우낭","823"],["jjang05","244012635","\/\/liveimg.afreecatv.com\/m\/244012635?533","주식왕짱다 ","710"],["dmsgkdn12","244012304","\/\/liveimg.afreecatv.com\/m\/244012304?43","[신입N여캠] 대상투표 꾸욱 ''♥'' 2부 프로듀스엔돌핀 있더연","305"],["k3938990","244013862","\/\/liveimg.afreecatv.com\/m\/244013862?59","저에게 딸이 있어요 맨만숙의 대구육아방송","58"],["didi5252","243938125","\/\/liveimg.afreecatv.com\/m\/243938125?379","순방시 500개 도전!!!!!!!!!!!! 롤토체스\/TFT","3466"],["arinbbidol","244013420","\/\/liveimg.afreecatv.com\/m\/244013420?488","기뉴다x유나땅 오버워치 ","1915"],["onlysibar","244012818","\/\/liveimg.afreecatv.com\/m\/244012818?802","스타 샤이니 테란 레더강의 맛집 보고S못찍으면 저그하세요?!","373"],["love1uu","244006578","\/\/liveimg.afreecatv.com\/m\/244006578?904","혜미x프로오빠 배틀그라운드 ㅎ","261"],["gjgj3274","244012898","\/\/liveimg.afreecatv.com\/m\/244012898?33","스타 래더 1등 이소룡 고민상담+래더강의 ","218"],["95yvely","244013711","\/\/liveimg.afreecatv.com\/m\/244013711?361","[바스포드] 일일카페 하고 허리 나갔음...","165"],["mingee1030","244012036","\/\/liveimg.afreecatv.com\/m\/244012036?220","AP 미드로 다이아 복구하기 승리 시 퀵뷰 뿌림.","161"],["wodnr7872","244013130","\/\/liveimg.afreecatv.com\/m\/244013130?516","[겐세이박] with빵주둥,초난강 3:3 5연승미션 스타 팀플 빨무 아마대","115"],["doeupzi","244012237","\/\/liveimg.afreecatv.com\/m\/244012237?60","비경한번 등반해보자 도읍지 원신","88"],["wjddlf4695","244013831","\/\/liveimg.afreecatv.com\/m\/244013831?162","스타 마이너즈 짭호 H I ","64"],["rladuddo99","244013141","\/\/liveimg.afreecatv.com\/m\/244013141?959","[바스포드]스진남 구성훈 vs원선재 3\/2...","54"],["zealot0846","244013651","\/\/liveimg.afreecatv.com\/m\/244013651?954","스타 토스 원선재 토스의 정석방송 vs 잉어킹형님 3\/2","40"],["killkg2","244013608","\/\/liveimg.afreecatv.com\/m\/244013608?841","건욱x승훈 v4 V4 마리온에서 전쟁중","32"],["koo2202","244012539","\/\/liveimg.afreecatv.com\/m\/244012539?850","[괴인협회]지연X리피피X리톨 괴토체스 조경훈의 제1충신","30"],["phh95426","244004912","\/\/liveimg.afreecatv.com\/m\/244004912?306","[24시간노잠방] 롤토체스 TFT 첼린저 갑니다. 시참,미션받아여","22"],["byebye22","244013891","\/\/liveimg.afreecatv.com\/m\/244013891?161","스타 애공이 하이하이 오랜만에 캠방똥","21"],["wldus5565","244012621","\/\/liveimg.afreecatv.com\/m\/244012621?528","[괴인협회] 혜지지 안녕하세요 괴인체스 !","19"],["bts150","244013294","\/\/liveimg.afreecatv.com\/m\/244013294?646","NSU 스타 방태수 래더 저그","16"],["eeceec","244013119","\/\/liveimg.afreecatv.com\/m\/244013119?515","아마대  1800  래더시 3만개 현재 1660","15"]],{"캄성":1,"우끼끼즈":0,"바스포드":3,"CP":1,"철와대":3,"NSU":1,"JSA":2,"무친대":0,"아마대":6,"츠나대":1,"MSG":1,"고대학":2}]