[[["kangjikk","243198208","\/\/liveimg.afreecatv.com\/m\/243198208?422","[JSA] 잠들기전 스타하깅 만다 vs 수핸 3\/2","163"],["ghtjs3833","243192008","\/\/liveimg.afreecatv.com\/m\/243192008?723","[JSA] 스타 최호선 48시간 노방종.. 만다vs수핸 3\/2","129"],["dodenvoa","243197352","\/\/liveimg.afreecatv.com\/m\/243197352?261","[JSA] 새벽반 다시 시작입니다 ","79"],["tv112","243199454","\/\/liveimg.afreecatv.com\/m\/243199454?721","우끼끼즈 수핸 )  조콤만 쉴게욤!!","65"],["askl021","243195773","\/\/liveimg.afreecatv.com\/m\/243195773?862","JSA 빡죠스 마꼬vs만다 뇌대리 각방 300개빵","59"],["oi123456","243194768","\/\/liveimg.afreecatv.com\/m\/243194768?870","♡JSA♡  6티어 꼬리..ㅎ","52"],["rlarnfk24","243201928","\/\/liveimg.afreecatv.com\/m\/243201928?328","스타 테란 ㅎㅇㅎㅇ","21"],["wodnr7872","243202159","\/\/liveimg.afreecatv.com\/m\/243202159?270","[겐세이박][아마대] 아침부터 유민님이랑..펑고 스타 팀플 빨무 탑툰","17"],["minyoo3972","243202111","\/\/liveimg.afreecatv.com\/m\/243202111?805","[우끼끼즈] 유민 vs 겐세이박 연습겜 프로필촬영가기전에","8"],["bobun","243202173","\/\/liveimg.afreecatv.com\/m\/243202173?262","GOU 눈뜬김에 연습=_=  (대회스폰40\/40 ,  학교숙제 스폰7\/100 (10\/18~)","4"],["bigbigjo2","243197094","\/\/liveimg.afreecatv.com\/m\/243197094?569","『드래곤볼Z』\"최고화질\"시청하면 퀵뷰드립니다♥(애니\/만화\/뉴스\/WWE\/나루토\/디지몬\/검정고무신\/코난\/이누야샤\/호빵맨\/원피스)","36"],["ain718","243199850","\/\/liveimg.afreecatv.com\/m\/243199850?322","신입여캠 비상비상!♥ #큰손쉼터 #노래 #음악 #음비 #뽑기","11"],["wnstn0905","243195928","\/\/liveimg.afreecatv.com\/m\/243195928?483","박사장 배틀그라운드 사비 10000개빵","1315"],["gudcjf604","243193040","\/\/liveimg.afreecatv.com\/m\/243193040?891","블랙워크 배그풍선랜드 사비빵 슈우웃 80킬내기  nsu","1074"],["xiaoeun","243200411","\/\/liveimg.afreecatv.com\/m\/243200411?712","히트2 시작합니다","801"],["girlbbo","243194537","\/\/liveimg.afreecatv.com\/m\/243194537?787","사비빵의 낭만","695"],["townboy","243196846","\/\/liveimg.afreecatv.com\/m\/243196846?577","스맵임니당 배그의신","649"],["kangjikk","243198208","\/\/liveimg.afreecatv.com\/m\/243198208?799","[JSA] 잠들기전 스타하깅 만다 vs 수핸 3\/2","163"],["ghtjs3833","243192008","\/\/liveimg.afreecatv.com\/m\/243192008?63","[JSA] 스타 최호선 48시간 노방종.. 만다vs수핸 3\/2","129"],["dodenvoa","243197352","\/\/liveimg.afreecatv.com\/m\/243197352?786","[JSA] 새벽반 다시 시작입니다 ","79"],["tv112","243199454","\/\/liveimg.afreecatv.com\/m\/243199454?460","우끼끼즈 수핸 )  조콤만 쉴게욤!!","65"],["askl021","243195773","\/\/liveimg.afreecatv.com\/m\/243195773?595","JSA 빡죠스 마꼬vs만다 뇌대리 각방 300개빵","59"],["oi123456","243194768","\/\/liveimg.afreecatv.com\/m\/243194768?134","♡JSA♡  6티어 꼬리..ㅎ","52"],["bogong","243194947","\/\/liveimg.afreecatv.com\/m\/243194947?162","레이지x수피x스맵x보고니 vs 블랙워크x박사장x걸뽀x히댕 4:4 킬내기!","47"],["rlarnfk24","243201928","\/\/liveimg.afreecatv.com\/m\/243201928?475","스타 테란 ㅎㅇㅎㅇ","21"],["wodnr7872","243202159","\/\/liveimg.afreecatv.com\/m\/243202159?451","[겐세이박][아마대] 아침부터 유민님이랑..펑고 스타 팀플 빨무 탑툰","17"]],{"캄성":0,"우끼끼즈":2,"바스포드":0,"CP":0,"철와대":0,"NSU":1,"JSA":5,"무친대":0,"아마대":1,"츠나대":0,"MSG":0,"고대학":1}]