[[["devil0108","243906318","\/\/liveimg.afreecatv.com\/m\/243906318?133","감스트 스타 ㄱㄱㄱㄱㄱㄱ","22510"],["rlaxordyd","243903807","\/\/liveimg.afreecatv.com\/m\/243903807?929","스타 김택용 메운디 26만개미션 22일차 끝가지간다...","2181"],["kkmkhh1234","243908418","\/\/liveimg.afreecatv.com\/m\/243908418?313","스타 깨모다 롤 듀오 with 디임","173"],["thetis","243906973","\/\/liveimg.afreecatv.com\/m\/243906973?443"," 스타 세나 테란전 연습중''-'' 저그 고수 훈수환영","25"],["lky6407","243908368","\/\/liveimg.afreecatv.com\/m\/243908368?716","[아마대] 토스 프발 래더 (2524\/2900)","24"],["kthrs9207","243905772","\/\/liveimg.afreecatv.com\/m\/243905772?248","스타 토스 파도 스타연습많이했다 바운디","20"],["bagguul","243900477","\/\/liveimg.afreecatv.com\/m\/243900477?589","[AMA] 아마대 규리야 자러감 100시간 노방종","17"],["wodnr7872","243908424","\/\/liveimg.afreecatv.com\/m\/243908424?204","[겐세이박][아마대] 규리,프발 빨무 스타 팀플 빨무 ","16"],["zealotmaru","243909307","\/\/liveimg.afreecatv.com\/m\/243909307?789","MSG 스타 토스  레더2700미션(12월23일생일)까지","8"],["skarbwhgc","243905779","\/\/liveimg.afreecatv.com\/m\/243905779?165","스타 테란 팔레트 래더 ","5"],["bbbaesiii","243909417","\/\/liveimg.afreecatv.com\/m\/243909417?998","텟","0"],["yochba0402","243904901","\/\/liveimg.afreecatv.com\/m\/243904901?902","[무세라핌] 졈니 졈스테리 이후 아웃라스트 공포게임 켠왕까지 달렸습ㄴㅣ다 ㄷㅠㄷ","742"],["devil0108","243906318","\/\/liveimg.afreecatv.com\/m\/243906318?826","감스트 스타 ㄱㄱㄱㄱㄱㄱ","22462"],["rrvv17","243900447","\/\/liveimg.afreecatv.com\/m\/243900447?853","킴성태x세아x나닝x싸패x사장x워크 남산등산벌칙","4629"],["lshooooo","243908768","\/\/liveimg.afreecatv.com\/m\/243908768?107","이상호 한일합작스쿼드 515 5연승시 팀갈가능 제발...","4533"],["rlaxordyd","243903807","\/\/liveimg.afreecatv.com\/m\/243903807?790","스타 김택용 메운디 26만개미션 22일차 끝가지간다...","2181"],["qpqpro","243908521","\/\/liveimg.afreecatv.com\/m\/243908521?255","상위 99% 아이언1 디임vs깨모다 롤 방종전 승리시 1500개 미션","576"],["killgusdnk","243903405","\/\/liveimg.afreecatv.com\/m\/243903405?872","클템\/ 에욱코 정글 승리시 1100 or 퀵뷰빵 ㄱ","505"],["clerver","243909164","\/\/liveimg.afreecatv.com\/m\/243909164?346","쿼드+스맵+강고+탈리+다랑 칼바람 딜량내기","445"],["dlghfjs","243889561","\/\/liveimg.afreecatv.com\/m\/243889561?111","깨박이 72시간 노방종 1시에 효딤이 집 방문 배틀그라운드","390"],["ys9024","243903341","\/\/liveimg.afreecatv.com\/m\/243903341?262","주서리","310"],["kkmkhh1234","243908418","\/\/liveimg.afreecatv.com\/m\/243908418?978","스타 깨모다 롤 듀오 with 디임","173"],["ckmin706","243907843","\/\/liveimg.afreecatv.com\/m\/243907843?149","플레티넘 미드 그리고 탑.. 민찬기","149"],["love1uu","243902151","\/\/liveimg.afreecatv.com\/m\/243902151?231","혜미 솔로치킨 3000개 배틀그라운드ㅎㅅㅎ","127"],["melong48","243902812","\/\/liveimg.afreecatv.com\/m\/243902812?869","럭뜨 솔배그 치킨시 2000개 ㅎㅅㅎ 훈수좀해쥬세요 ㅠㅠ","66"],["mudorl","243908391","\/\/liveimg.afreecatv.com\/m\/243908391?205","테란_나홀로 롱빈터..","37"],["thetis","243906973","\/\/liveimg.afreecatv.com\/m\/243906973?687"," 스타 세나 테란전 연습중''-'' 저그 고수 훈수환영","25"],["lky6407","243908368","\/\/liveimg.afreecatv.com\/m\/243908368?946","[아마대] 토스 프발 래더 (2524\/2900)","24"],["godnjs8482","243904479","\/\/liveimg.afreecatv.com\/m\/243904479?85","[BKG]소환사의 협공장 #BJ할배 #킬내기공장","22"],["vudwlqhdxb93","243902672","\/\/liveimg.afreecatv.com\/m\/243902672?196","[롤신입]소프트 x 김태빵 승당300개 9연패끈었다...딱한판만 이기자!!","21"],["kthrs9207","243905772","\/\/liveimg.afreecatv.com\/m\/243905772?516","스타 토스 파도 스타연습많이했다 바운디","20"],["oi123456","243906570","\/\/liveimg.afreecatv.com\/m\/243906570?766","♡전jsa♡ 방실이랑 !! 미숀 환영환영!!","18"],["bagguul","243900477","\/\/liveimg.afreecatv.com\/m\/243900477?734","[AMA] 아마대 규리야 자러감 100시간 노방종","17"],["wodnr7872","243908424","\/\/liveimg.afreecatv.com\/m\/243908424?728","[겐세이박][아마대] 규리,프발 빨무 스타 팀플 빨무 ","16"]],{"캄성":0,"우끼끼즈":0,"바스포드":1,"CP":1,"철와대":3,"NSU":1,"JSA":1,"무친대":6,"아마대":3,"츠나대":1,"MSG":1,"고대학":0}]