[[["bora99","247570059","\/\/liveimg.afreecatv.com\/m\/247570059?646","FA고민상담소 .. 뿌하 김무아님","2337"],["daegalheo","247569912","\/\/liveimg.afreecatv.com\/m\/247569912?60"," 허유 방긋다 스타 마이너즈","173"],["minyoo3972","247568905","\/\/liveimg.afreecatv.com\/m\/247568905?571","우끼끼즈 유민 굿모닝^^래더 잠깐 합니다 VS 허유님 3\/2 ;;","71"],["rpalwlq","247570675","\/\/liveimg.afreecatv.com\/m\/247570675?680","[우끼끼즈] 박영덕 대회얘기좀해보자","49"],["eeceec","247570174","\/\/liveimg.afreecatv.com\/m\/247570174?853","[흑]  지각 ㅠ\/테란은 하나다","47"],["jipsh2","247570589","\/\/liveimg.afreecatv.com\/m\/247570589?432","[스틱] 3vs3오후생 스타 팀플 헌터 늑대77연승 기록방송","14"],["bobun","247570727","\/\/liveimg.afreecatv.com\/m\/247570727?865","수학 저그 (구)조오리 뚜미랑 사비 스폰 3\/2 대기 스폰 걸어주실 귀인분 계신가뇨","10"],["lshooooo","247557386","\/\/liveimg.afreecatv.com\/m\/247557386?988","이상호 7~8시 기상예정 235시간 노방종 1일차 ","2219"],["ggangsoony","247569428","\/\/liveimg.afreecatv.com\/m\/247569428?401","[MC크루] 도착했습니다.월말결산하겠습니다.         \/맨만숙흥구기날박엠씨크루","244"],["killgusdnk","247569862","\/\/liveimg.afreecatv.com\/m\/247569862?104","클템.  lck 8주차찍어. 이젠1주남았다.. 달려보자 찍어x3 with 포니,동진!","3288"],["pkdlwpans","247563523","\/\/liveimg.afreecatv.com\/m\/247563523?55","[로나월드 시즌2] 싸패 검은해적단 랄드","2379"],["bora99","247570059","\/\/liveimg.afreecatv.com\/m\/247570059?990","FA고민상담소 .. 뿌하 김무아님","2338"],["legendhyuk","247570493","\/\/liveimg.afreecatv.com\/m\/247570493?733","에메랄드 모으기 운동 오스카 [ 로나월드:시즌2 ] ","2210"],["ogm0905","247513680","\/\/liveimg.afreecatv.com\/m\/247513680?920","오뀨 ㅎㅇ용 좋은아침 챌린저모험기 3만개 챌노방종","1275"],["didi5252","247497413","\/\/liveimg.afreecatv.com\/m\/247497413?397","씻는날이라 씻고옴다 쪼튜브 ㄱㄱ!","339"],["tjaudtn123","247568289","\/\/liveimg.afreecatv.com\/m\/247568289?981","서도일 찡찡X","282"],["daegalheo","247569912","\/\/liveimg.afreecatv.com\/m\/247569912?949"," 허유 방긋다 스타 마이너즈","173"],["minyoo3972","247568905","\/\/liveimg.afreecatv.com\/m\/247568905?651","우끼끼즈 유민 굿모닝^^래더 잠깐 합니다 VS 허유님 3\/2 ;;","71"],["whddnr2813","247568705","\/\/liveimg.afreecatv.com\/m\/247568705?335","맛종욱 로나월드:시즌2 자미안와요 ","71"],["raso0601","247569219","\/\/liveimg.afreecatv.com\/m\/247569219?528","좌뇌가 함몰된 건가요....?","52"],["rpalwlq","247570675","\/\/liveimg.afreecatv.com\/m\/247570675?799","[우끼끼즈] 박영덕 대회얘기좀해보자","50"],["eeceec","247570174","\/\/liveimg.afreecatv.com\/m\/247570174?533","[흑]  지각 ㅠ\/테란은 하나다","47"],["koo2202","247570416","\/\/liveimg.afreecatv.com\/m\/247570416?87","[유플릭스 지원자] 본이루","17"],["tjfwkdgks","247569661","\/\/liveimg.afreecatv.com\/m\/247569661?301","[변순대]라코 랭킹12등 부캐강의 시작합니다.[강의,라문철 가능]서폿 챌린저LOL","17"]],{"캄성":1,"우끼끼즈":2,"JSA":0,"보신대":0,"DP":0,"라이트클럽":1,"흑카데미":1,"철기빵":0,"YB":0,"석사관":0,"나사":0,"늪지대":0}]