[[["vlfvlf789","242665265","\/\/liveimg.afreecatv.com\/m\/242665265?428","MSG 저티어 억타련들 참교육 솜신 jsa 안보냅니다","1941"],["cnsgkcnehd74","242665293","\/\/liveimg.afreecatv.com\/m\/242665293?662","괴인협회 알로하 다과회 새로운 괴인을 소개합니다","1484"],["na2un","242658231","\/\/liveimg.afreecatv.com\/m\/242658231?750","NSU 숙제 ㅅㅂ","1131"],["imhappygood","242664914","\/\/liveimg.afreecatv.com\/m\/242664914?29","괴인협회&gt;스타뉴스&gt;드릴 사건이 있습니다 ...슈웃! \/철와대 무친대 바스포드 MSG NSU JSA CP GOU 아마대 우끼끼즈 캄성","803"],["onlysibar","242664922","\/\/liveimg.afreecatv.com\/m\/242664922?977","무친대 스타 샤이니 테란 MMR0부터~S까지 찍는 강의","409"],["tladl5572","242656470","\/\/liveimg.afreecatv.com\/m\/242656470?828","NSU 효딤 나닝 류하 남순 닝치원ㄴ_ㅇ^","296"],["123rhaxld","242665796","\/\/liveimg.afreecatv.com\/m\/242665796?411","[AMA] 아마대 굿모닝","118"],["wkddudrms15","242665303","\/\/liveimg.afreecatv.com\/m\/242665303?707","[아마대] 난수 기뉴다와 상담","97"],["palko1","242666090","\/\/liveimg.afreecatv.com\/m\/242666090?215","[우끼끼즈] 신상문 새 스튜디오 첫방 ","94"],["dodenvoa","242663959","\/\/liveimg.afreecatv.com\/m\/242663959?344","[JSA] 새벽... 묵언스타 ","87"],["ovoa3316","242665880","\/\/liveimg.afreecatv.com\/m\/242665880?882","아마대 나예리 좋은 오전  탕치고","50"],["wjddlf4695","242666043","\/\/liveimg.afreecatv.com\/m\/242666043?936","[AMA] 아마대 짭호 ㅎㅇㅎㅇ","40"],["rladuddo99","242665802","\/\/liveimg.afreecatv.com\/m\/242665802?519","[바스포드]스타 구성훈 모잉와이드","30"],["simcheong23","242664820","\/\/liveimg.afreecatv.com\/m\/242664820?321","스타 MSG 또봉순  FA분들 실력구경","30"],["melong48","242656476","\/\/liveimg.afreecatv.com\/m\/242656476?131","무친대 럭뜨 24시간 노방죵;","28"],["wnsgur2da","242665940","\/\/liveimg.afreecatv.com\/m\/242665940?333","[철와대]얍삽e 스타 래더 vs샤순신 3\/2","21"],["raso0601","242665947","\/\/liveimg.afreecatv.com\/m\/242665947?246","[AMA][괴인협회] 아마대 굿모닝 하요야!","18"],["loveda91","242665002","\/\/liveimg.afreecatv.com\/m\/242665002?256"," DIC 루키즈  테란 연도기구함","15"],["bagguul","242665956","\/\/liveimg.afreecatv.com\/m\/242665956?960","[AMA]아마대 규리야vs msg 단판200개","14"],["xshinx","242666031","\/\/liveimg.afreecatv.com\/m\/242666031?884","아마대 안녕하세오 +ㅅ +* ","12"],["ddd001","242665921","\/\/liveimg.afreecatv.com\/m\/242665921?614","MSG) 하이이이이","12"],["qndnd12","242664722","\/\/liveimg.afreecatv.com\/m\/242664722?170","[AMA]아마대 스타 저그 알렌 반갑습니당","11"],["dbrbals","242665590","\/\/liveimg.afreecatv.com\/m\/242665590?798","아마대 초난강 ","8"],["rhsqlsu","242666046","\/\/liveimg.afreecatv.com\/m\/242666046?646","[MSG]지망생 2주간 폼올리기 ","3"],["wodnr7872","242666171","\/\/liveimg.afreecatv.com\/m\/242666171?160","[겐세이박][아마대] hi스타 팀플 빨무 ","0"],["arinbbidol","242665290","\/\/liveimg.afreecatv.com\/m\/242665290?144","기뉴다 상담좀 받겠습니다.","5088"],["wnnw","242628653","\/\/liveimg.afreecatv.com\/m\/242628653?964","남순 취침중 기상 12시기상 72시간 마지막날","2716"],["dmsgkdn12","242595602","\/\/liveimg.afreecatv.com\/m\/242595602?6","[신입여캠] JSA서쫑알 합방♥   사라짱 266시간 노방종 ♥ ","133"],["wnstn0905","242652389","\/\/liveimg.afreecatv.com\/m\/242652389?202","박사장 400시간 죄송합니다 슬럼프에요 주제파악하면서 살겠습니다 배틀그라운드","64"],["chuchu0517","242665174","\/\/liveimg.afreecatv.com\/m\/242665174?177","♥신입여캠2일차♥ 안녕굿모닝♥ 1454정성방셀+역팬♥","7"],["vlfvlf789","242665265","\/\/liveimg.afreecatv.com\/m\/242665265?837","MSG 저티어 억타련들 참교육 솜신 jsa 안보냅니다","1941"],["cnsgkcnehd74","242665293","\/\/liveimg.afreecatv.com\/m\/242665293?362","괴인협회 알로하 다과회 새로운 괴인을 소개합니다","1484"],["na2un","242658231","\/\/liveimg.afreecatv.com\/m\/242658231?775","NSU 숙제 ㅅㅂ","1131"],["didi5252","242665338","\/\/liveimg.afreecatv.com\/m\/242665338?625","핫픽스 실화?! 새메타를 찾는 삐롱쏴 TFT\/ 롤토체스","1060"],["imhappygood","242664914","\/\/liveimg.afreecatv.com\/m\/242664914?113","괴인협회&gt;스타뉴스&gt;드릴 사건이 있습니다 ...슈웃! \/철와대 무친대 바스포드 MSG NSU JSA CP GOU 아마대 우끼끼즈 캄성","803"],["onlysibar","242664922","\/\/liveimg.afreecatv.com\/m\/242664922?768","무친대 스타 샤이니 테란 MMR0부터~S까지 찍는 강의","409"],["tladl5572","242656470","\/\/liveimg.afreecatv.com\/m\/242656470?949","NSU 효딤 나닝 류하 남순 닝치원ㄴ_ㅇ^","296"],["mightybear","242665702","\/\/liveimg.afreecatv.com\/m\/242665702?816","[철와대] 마베 롤 멸망전 족장님팀 어제경기 피드백","166"],["tmdwn0314","242663701","\/\/liveimg.afreecatv.com\/m\/242663701?905","아펠 너프 근데 아직 쌤  롤토체스 TFT [괴인협회]","150"],["123rhaxld","242665796","\/\/liveimg.afreecatv.com\/m\/242665796?404","[AMA] 아마대 굿모닝","118"],["ckdrnrdl1234","242665933","\/\/liveimg.afreecatv.com\/m\/242665933?835","[생]본캐 더이상 못해먹겠네요 성능으로 리빌딩할게요 피파4","99"],["wkddudrms15","242665303","\/\/liveimg.afreecatv.com\/m\/242665303?911","[아마대] 난수 기뉴다와 상담","97"],["palko1","242666090","\/\/liveimg.afreecatv.com\/m\/242666090?303","[우끼끼즈] 신상문 새 스튜디오 첫방 ","94"],["dodenvoa","242663959","\/\/liveimg.afreecatv.com\/m\/242663959?314","[JSA] 새벽... 묵언스타 ","85"],["ovoa3316","242665880","\/\/liveimg.afreecatv.com\/m\/242665880?375","아마대 나예리 좋은 오전  탕치고","50"],["wjddlf4695","242666043","\/\/liveimg.afreecatv.com\/m\/242666043?333","[AMA] 아마대 짭호 ㅎㅇㅎㅇ","40"],["rladuddo99","242665802","\/\/liveimg.afreecatv.com\/m\/242665802?663","[바스포드]스타 구성훈 모잉와이드","30"],["simcheong23","242664820","\/\/liveimg.afreecatv.com\/m\/242664820?370","스타 MSG 또봉순  FA분들 실력구경","30"],["melong48","242656476","\/\/liveimg.afreecatv.com\/m\/242656476?672","무친대 럭뜨 24시간 노방죵;","28"],["wnsgur2da","242665940","\/\/liveimg.afreecatv.com\/m\/242665940?933","[철와대]얍삽e 스타 래더 vs샤순신 3\/2","21"],["raso0601","242665947","\/\/liveimg.afreecatv.com\/m\/242665947?459","[AMA][괴인협회] 아마대 굿모닝 하요야!","16"],["loveda91","242665002","\/\/liveimg.afreecatv.com\/m\/242665002?840"," DIC 루키즈  테란 연도기구함","15"],["dlangusrnt","242663641","\/\/liveimg.afreecatv.com\/m\/242663641?511","무돌 잠안잤다... 소통 배틀그라운드","10"]],{"캄성":0,"우끼끼즈":1,"바스포드":2,"CP":0,"철와대":2,"NSU":3,"JSA":1,"무친대":3,"아마대":10,"츠나대":0,"MSG":3,"고대학":0}]