[[["superbsw123","246551361","\/\/liveimg.afreecatv.com\/m\/246551361?731","JSA)후,.,올것이 왔습니다..","6838"],["cztaemin","246551531","\/\/liveimg.afreecatv.com\/m\/246551531?537","보신대 총장 천태민 보신대 8티어 선발전 피의전쟁 1경기 링고 vs 짱이쥬","697"],["tjdwnls123","246551540","\/\/liveimg.afreecatv.com\/m\/246551540?876","석사관 mt 갑니다","530"],["onlysibar","246550523","\/\/liveimg.afreecatv.com\/m\/246550523?46","스타 샤이니 테란 S못찍으면 이니형이 팰지도모르는?? 레더강의","279"],["rnjsgurwls15","246550095","\/\/liveimg.afreecatv.com\/m\/246550095?941","보신대 권혁진 토스 8티어 선발전 ","101"],["rpalwlq","246551248","\/\/liveimg.afreecatv.com\/m\/246551248?144","[우끼끼즈] 감전동 SCV 출동완료!!","86"],["kangjikk","246551661","\/\/liveimg.afreecatv.com\/m\/246551661?342","YB 만다 ck하러와써염","74"],["lyh8808","246551277","\/\/liveimg.afreecatv.com\/m\/246551277?82","보신대)스타 이영한 디코 점호","64"],["snowssa","246551268","\/\/liveimg.afreecatv.com\/m\/246551268?138","보신대 8티어 벌레대전 퇴학빵 부천스타","34"],["yyh3397","246549770","\/\/liveimg.afreecatv.com\/m\/246549770?909","[NASA] 독감연구소 독감CK 대기중","33"],["hy4985","246550420","\/\/liveimg.afreecatv.com\/m\/246550420?377","[보신대]옆집뽀누나!  스타   기본기연습하면서 이사장님 구경","32"],["ldk8481","246551260","\/\/liveimg.afreecatv.com\/m\/246551260?7","[보신대\/JBF] 보신대 점호 왔습니다 *7티어 저그*","31"],["kitty1029","246551240","\/\/liveimg.afreecatv.com\/m\/246551240?690","보신대 꼬니부깅 11시 점호! ","27"],["aaaa7979","246550964","\/\/liveimg.afreecatv.com\/m\/246550964?177"," 토스 7 애는 착,.,,해요 ... ","20"],["suji84","246551247","\/\/liveimg.afreecatv.com\/m\/246551247?490","[ 보신대 엔치원 ] 11시 디코점호","15"],["soonja2021","246550888","\/\/liveimg.afreecatv.com\/m\/246550888?127","[보신대] 11시점호!!!!","12"],["wjswpalssla1","246551663","\/\/liveimg.afreecatv.com\/m\/246551663?364","[라이트클럽 마이너즈] 스타 전제민 밥좀먹을꼐연","11"],["bhy95","246551626","\/\/liveimg.afreecatv.com\/m\/246551626?261","스타 테란 잭티어 배호연 재활1일차","10"],["qndnd12","246551283","\/\/liveimg.afreecatv.com\/m\/246551283?826","[NASA] 나사 스타 저그 알렌 아픈것도 죽어서 아프자 (독감CK 합니다 형님들 도와주세요)","8"],["dmsthfdldia","246551194","\/\/liveimg.afreecatv.com\/m\/246551194?716","[보신대]안뇽하세요 무한펑고 연도기님 구합니다!","6"],["eun9116","246551188","\/\/liveimg.afreecatv.com\/m\/246551188?626","[보신대]굿모닝!~ 비글토스 ","6"],["khc2566","246551275","\/\/liveimg.afreecatv.com\/m\/246551275?793","[보신대]코치 라히 8티어 끝장전 매정하게 평가할게요 #구듀윌 #정중만","1"],["vlfvlf789","246551013","\/\/liveimg.afreecatv.com\/m\/246551013?510","수니그룹 이누나 왜이리이뻐","2749"],["mb8987","246551767","\/\/liveimg.afreecatv.com\/m\/246551767?980","[케크루]내일 결전의 날입니다.","83"],["bigbigjo2","246494900","\/\/liveimg.afreecatv.com\/m\/246494900?849","『드래곤볼Z』\"최초공개\"시청하면 퀵뷰드립니다♥(애니\/만화\/뉴스\/WWE\/나루토\/\/마음의소리\/코난\/이누야샤\/호빵맨\/원피스\/맛있는녀석들)","18"],["jinhi1004","246542430","\/\/liveimg.afreecatv.com\/m\/246542430?87","982킬 노뱅종 으아아아 !! 8시에올게용!!","15"],["superbsw123","246551361","\/\/liveimg.afreecatv.com\/m\/246551361?373","JSA)후,.,올것이 왔습니다..","6948"],["cztaemin","246551531","\/\/liveimg.afreecatv.com\/m\/246551531?149","보신대 총장 천태민 보신대 8티어 선발전 피의전쟁 1경기 링고 vs 짱이쥬","697"],["tjdwnls123","246551540","\/\/liveimg.afreecatv.com\/m\/246551540?471","석사관 mt 갑니다","530"],["tjaudtn123","246549989","\/\/liveimg.afreecatv.com\/m\/246549989?811","서도일 정글랭킹1등 지망생","329"],["onlysibar","246550523","\/\/liveimg.afreecatv.com\/m\/246550523?256","스타 샤이니 테란 S못찍으면 이니형이 팰지도모르는?? 레더강의","278"],["giltae1124","246550344","\/\/liveimg.afreecatv.com\/m\/246550344?968","롤체 개고수등장 마스터 200점","194"],["rnjsgurwls15","246550095","\/\/liveimg.afreecatv.com\/m\/246550095?123","보신대 권혁진 토스 8티어 선발전 ","101"],["rpalwlq","246551248","\/\/liveimg.afreecatv.com\/m\/246551248?75","[우끼끼즈] 감전동 SCV 출동완료!!","86"],["kangjikk","246551661","\/\/liveimg.afreecatv.com\/m\/246551661?223","YB 만다 ck하러와써염","74"],["lyh8808","246551277","\/\/liveimg.afreecatv.com\/m\/246551277?694","보신대)스타 이영한 디코 점호","64"],["raso0601","246551058","\/\/liveimg.afreecatv.com\/m\/246551058?542","실4 빨딱중 제일 이쁜애 ^0^ #구듀윌","38"],["snowssa","246551268","\/\/liveimg.afreecatv.com\/m\/246551268?667","보신대 8티어 벌레대전 퇴학빵 부천스타","34"],["yyh3397","246549770","\/\/liveimg.afreecatv.com\/m\/246549770?290","[NASA] 독감연구소 독감CK 대기중","33"],["koo2202","246551595","\/\/liveimg.afreecatv.com\/m\/246551595?989","[퐁퐁\/괴인] 점심식사","32"],["hy4985","246550420","\/\/liveimg.afreecatv.com\/m\/246550420?951","[보신대]옆집뽀누나!  스타   기본기연습하면서 이사장님 구경","32"],["ldk8481","246551260","\/\/liveimg.afreecatv.com\/m\/246551260?499","[보신대\/JBF] 보신대 점호 왔습니다 *7티어 저그*","31"],["kitty1029","246551240","\/\/liveimg.afreecatv.com\/m\/246551240?989","보신대 꼬니부깅 11시 점호! ","27"],["vudwlqhdxb93","246550183","\/\/liveimg.afreecatv.com\/m\/246550183?530","솔랭전사 브4 아침을여는 행복롤 시작~","22"],["aaaa7979","246550964","\/\/liveimg.afreecatv.com\/m\/246550964?132"," 토스 7 애는 착,.,,해요 ... ","20"],["qkrgkdms01","246488451","\/\/liveimg.afreecatv.com\/m\/246488451?486","광우상사 대기방              광우상사 지코","442"],["e9dongsung","246551745","\/\/liveimg.afreecatv.com\/m\/246551745?221","정오텐트 (5월 24일 수요일)","192"]],{"캄성":0,"우끼끼즈":2,"바스포드":1,"CP":3,"철와대":0,"NSU":0,"JSA":3,"무친대":0,"아마대":4,"츠나대":0,"MSG":2,"고대학":3}]