[[["wjddlf4695","245354952","\/\/liveimg.afreecatv.com\/m\/245354952?681","[철기구치소][마이너즈] 짭호 쇼타임","107"],["wodnr7872","245353758","\/\/liveimg.afreecatv.com\/m\/245353758?511","[겐세이박] ㅎㅇ;ㅎㅇ; 스타 팀플 빨무","97"],["starobba","245354836","\/\/liveimg.afreecatv.com\/m\/245354836?482","이승훈 마이너즈 쇼타임 스타랜능크","61"],["khy12088ws","245353591","\/\/liveimg.afreecatv.com\/m\/245353591?169","스타 토스 저티어강의","40"],["clclcl8888","245315178","\/\/liveimg.afreecatv.com\/m\/245315178?724","100시간 노방종 \/ 오후 출몰예정","36"],["toozi0317","245353599","\/\/liveimg.afreecatv.com\/m\/245353599?568","스타 테란 이인극  모닝래도..","24"],["qndnd12","245354290","\/\/liveimg.afreecatv.com\/m\/245354290?18","스타 저그 알렌 안녕하세욤","17"],["haru1207","245354934","\/\/liveimg.afreecatv.com\/m\/245354934?749","[생] 빨무응애등장 ! 미션환영 ! ","10"],["hy4985","245354416","\/\/liveimg.afreecatv.com\/m\/245354416?674","옆집뽀누나  스타  굿모닝","9"],["rnjsgurwls15","245354976","\/\/liveimg.afreecatv.com\/m\/245354976?521","스타 마이너즈 권혁진 아침 쇼타임~~","8"],["soonja2021","245354958","\/\/liveimg.afreecatv.com\/m\/245354958?226","스타 나에게 지면 누구에게도 이길 수 없다.","5"],["killkg2","245355000","\/\/liveimg.afreecatv.com\/m\/245355000?528","스타 마이너즈 건욱 쇼타임","3"],["drumkyn","245354144","\/\/liveimg.afreecatv.com\/m\/245354144?811","주식왕용느★[인생찐찐찐막시즌]유쾌함이 사라진곳입니다.","2854"],["jjang05","245354151","\/\/liveimg.afreecatv.com\/m\/245354151?931","⭐ 끝날때까지 끝난게 아니다 ⭐","380"],["yunhee1222","245353329","\/\/liveimg.afreecatv.com\/m\/245353329?861","[수니그룹2%] 살려주세요","124"],["snfjdro369","245330276","\/\/liveimg.afreecatv.com\/m\/245330276?28","스타 윤수철 2~3시에옴.","7"],["phh95426","245343452","\/\/liveimg.afreecatv.com\/m\/245343452?321","[만스터치] 24시간노방종... 연습하고 자고올게염","6"],["ceri123","245354213","\/\/liveimg.afreecatv.com\/m\/245354213?770","불사조 5000개 호랑이 1000개 찾기 [로나월드:서수길 골드문]  ๑°⌓°๑ ","416"],["qks717cks","245343893","\/\/liveimg.afreecatv.com\/m\/245343893?186","20년도 웁 틀고 자고옴 ㅎㅎ 다이아2768개 노방종.. 무파 정식 사원 [로나월드:서수길]","409"],["giltae1124","245354698","\/\/liveimg.afreecatv.com\/m\/245354698?297","라면을 먹고시작하지.","375"],["moonwol0614","245350055","\/\/liveimg.afreecatv.com\/m\/245350055?581","행복하고 평화로운 협.곡","368"],["didi5252","245340517","\/\/liveimg.afreecatv.com\/m\/245340517?154","기사아아앙!!!! 씻고옴!","172"],["osim0408","245354591","\/\/liveimg.afreecatv.com\/m\/245354591?621","C1 670 오랜만입니당","136"],["wjddlf4695","245354952","\/\/liveimg.afreecatv.com\/m\/245354952?917","[철기구치소][마이너즈] 짭호 쇼타임","109"],["chajs0070","245353841","\/\/liveimg.afreecatv.com\/m\/245353841?720","퐁퐁랜드 기라클 차인턴 앤다드레곤잡기^^","102"],["wodnr7872","245353758","\/\/liveimg.afreecatv.com\/m\/245353758?255","[겐세이박] ㅎㅇ;ㅎㅇ; 스타 팀플 빨무","95"],["starobba","245354836","\/\/liveimg.afreecatv.com\/m\/245354836?685","이승훈 마이너즈 쇼타임 스타랜능크","62"],["khy12088ws","245353591","\/\/liveimg.afreecatv.com\/m\/245353591?776","스타 토스 저티어강의","40"],["dlangusrnt","245342857","\/\/liveimg.afreecatv.com\/m\/245342857?242","무돌 하청업체 3파전 배틀그라운드","36"],["clclcl8888","245315178","\/\/liveimg.afreecatv.com\/m\/245315178?408","100시간 노방종 \/ 오후 출몰예정","36"],["toozi0317","245353599","\/\/liveimg.afreecatv.com\/m\/245353599?142","스타 테란 이인극  모닝래도..","24"],["koo2202","245354166","\/\/liveimg.afreecatv.com\/m\/245354166?314","[퐁퐁\/괴인] 본이루","20"],["qndnd12","245354290","\/\/liveimg.afreecatv.com\/m\/245354290?452","스타 저그 알렌 안녕하세욤","17"],["gjgj3274","245354392","\/\/liveimg.afreecatv.com\/m\/245354392?886","[스포츠분석가]껌광이복귀했다.NBA  필라 인디 포틀 디트 보스턴 클블농구 분석 중계 3월 출발 치킨-50 치킨OR퀵뷰 고민상담 소룡","101"]],{"캄성":2,"우끼끼즈":0,"바스포드":2,"CP":3,"철와대":1,"NSU":0,"JSA":1,"무친대":1,"아마대":3,"츠나대":2,"MSG":1,"고대학":1}]