[[["gef456","245698575","\/\/liveimg.afreecatv.com\/m\/245698575?107","밀진남 테란 \"2티어 정민기\" S못찍으면 한강 Dive..","25"],["jh3697","245698645","\/\/liveimg.afreecatv.com\/m\/245698645?770","스타 서문지훈 모닝래더방송 어떤데 저그","20"],["skarbwhgc","245698450","\/\/liveimg.afreecatv.com\/m\/245698450?325","스타 테란 팔레트 래더 수련 ","5"],["rrvv17","245698472","\/\/liveimg.afreecatv.com\/m\/245698472?999","킴성태x봉준 롤미션받습니다 ","7102"],["giltae1124","245698453","\/\/liveimg.afreecatv.com\/m\/245698453?981","몰락크라켄 애쉬간드아","327"],["watchfact","245698628","\/\/liveimg.afreecatv.com\/m\/245698628?52","퐁퐁 와치 내가 레인코인 떡상 한다했제? 츠기오때","55"],["gef456","245698575","\/\/liveimg.afreecatv.com\/m\/245698575?80","밀진남 테란 \"2티어 정민기\" S못찍으면 한강 Dive..","25"],["jh3697","245698645","\/\/liveimg.afreecatv.com\/m\/245698645?920","스타 서문지훈 모닝래더방송 어떤데 저그","20"],["dlangusrnt","245698705","\/\/liveimg.afreecatv.com\/m\/245698705?898","무돌 배틀그라운드 카테고리 아침뉴스 ","11"],["skarbwhgc","245698450","\/\/liveimg.afreecatv.com\/m\/245698450?626","스타 테란 팔레트 래더 수련 ","5"]],{"캄성":0,"우끼끼즈":0,"바스포드":0,"CP":0,"철와대":1,"NSU":1,"JSA":0,"무친대":1,"아마대":0,"츠나대":0,"MSG":1,"고대학":1}]