[[["wlsrl2566","246843990","\/\/liveimg.afreecatv.com\/m\/246843990?941","NASA 저그인원들 다 불렀습니다 저그CK 3경기 배성흠 0 VS 2 지동원","1657"],["cztaemin","246844681","\/\/liveimg.afreecatv.com\/m\/246844681?857","보신대 총장 박태민 비방 연습..가는길 힘내자! ㅡㅡㅡ부천정중만","542"],["ehgmldud1233","246840039","\/\/liveimg.afreecatv.com\/m\/246840039?366","[흑] 히엉 나사CK 출전..","300"],["hy4985","246843945","\/\/liveimg.afreecatv.com\/m\/246843945?410","옆집뽀누나☆보신대스타. 운동어떻게해야하나","211"],["wkddudrms15","246844608","\/\/liveimg.afreecatv.com\/m\/246844608?638","[늪지대] 난수 조커로서 실력키우기","163"],["rondobba","246844868","\/\/liveimg.afreecatv.com\/m\/246844868?57","[우끼끼즈]지동원 나사CK vs 배성흠","118"],["rfvtgb778","246843016","\/\/liveimg.afreecatv.com\/m\/246843016?112","스타 이영웅 래더 한번보면 쉽게S가는 쉬운강의^^","111"],["simcheong23","246844116","\/\/liveimg.afreecatv.com\/m\/246844116?863","[보신대] 또봉순 종변해보겠씁니다 테란으로","77"],["dpfkd99","246844816","\/\/liveimg.afreecatv.com\/m\/246844816?401","[석사관]-------ㅎㅇ-------\/ 카단 블래스터 로아 성예량","48"],["bbbaesiii","246844912","\/\/liveimg.afreecatv.com\/m\/246844912?574","나사 저그ck 참여 상대 쥬나","43"],["jscando77","246844740","\/\/liveimg.afreecatv.com\/m\/246844740?212","[석사관] 인력석무소 나사 저그ck 몽순님 상대&gt;.&lt;","40"],["by0529","246843543","\/\/liveimg.afreecatv.com\/m\/246843543?182","수뿌 모닝재활래더 S찍기","32"],["pazzy1","246845080","\/\/liveimg.afreecatv.com\/m\/246845080?91","[우끼끼즈] 파찌 화장중","31"],["kalmian","246843924","\/\/liveimg.afreecatv.com\/m\/246843924?270","[석사관] 토스봇 @_@ 안녕하세요 \/\/ 11시 인력사무소!!","23"],["ddd001","246844842","\/\/liveimg.afreecatv.com\/m\/246844842?830","[석사관] 인력사무소!!","21"],["do33ob","246844318","\/\/liveimg.afreecatv.com\/m\/246844318?34","8티어 풀리그 펀딩 귀인 모십니다 ㅇ.ㅇ","20"],["starstim","246843468","\/\/liveimg.afreecatv.com\/m\/246843468?456","스타 테란 탱구화이트 NASA CK 참가","16"],["wpwpwp119","246844648","\/\/liveimg.afreecatv.com\/m\/246844648?571","스타 테란 배지웅 모닝래더ㅎ.ㅎ","14"],["snowssa","246836110","\/\/liveimg.afreecatv.com\/m\/246836110?213","[보신대] 또 24시간.. 4시 기상 깨워 깨우지마 전자녀 10개...  부천스타정중만","14"],["vlfvlf789","246844375","\/\/liveimg.afreecatv.com\/m\/246844375?964","수니그룹E 제발 그만좀하세요","2567"],["apple1004l","246845039","\/\/liveimg.afreecatv.com\/m\/246845039?834","(향기빵)","698"],["jjang05","246843963","\/\/liveimg.afreecatv.com\/m\/246843963?236","ㅅㅂ잠이나 잘걸","350"],["bigbigjo2","246775507","\/\/liveimg.afreecatv.com\/m\/246775507?139","『검정고무신』\"최초공개\"시청하면 퀵뷰드립니다♥(애니\/만화\/뉴스\/WWE\/나루토\/드래곤볼\/마음의소리\/코난\/이누야샤\/호빵맨\/원피스)","23"],["wlsrl2566","246843990","\/\/liveimg.afreecatv.com\/m\/246843990?835","NASA 저그인원들 다 불렀습니다 저그CK 3경기 배성흠 0 VS 2 지동원","1660"],["cztaemin","246844681","\/\/liveimg.afreecatv.com\/m\/246844681?444","보신대 총장 박태민 비방 연습..가는길 힘내자! ㅡㅡㅡ부천정중만","541"],["ehgmldud1233","246840039","\/\/liveimg.afreecatv.com\/m\/246840039?675","[흑] 히엉 나사CK 출전..","303"],["hy4985","246843945","\/\/liveimg.afreecatv.com\/m\/246843945?191","옆집뽀누나☆보신대스타. 운동어떻게해야하나","211"],["wkddudrms15","246844608","\/\/liveimg.afreecatv.com\/m\/246844608?15","[늪지대] 난수 조커로서 실력키우기","163"],["tjaudtn123","246844461","\/\/liveimg.afreecatv.com\/m\/246844461?1000","도일 안녕하세령","123"],["rondobba","246844868","\/\/liveimg.afreecatv.com\/m\/246844868?163","[우끼끼즈]지동원 나사CK vs 배성흠","118"],["rfvtgb778","246843016","\/\/liveimg.afreecatv.com\/m\/246843016?307","스타 이영웅 래더 한번보면 쉽게S가는 쉬운강의^^","111"],["simcheong23","246844116","\/\/liveimg.afreecatv.com\/m\/246844116?606","[보신대] 또봉순 종변해보겠씁니다 테란으로","77"],["dpfkd99","246844816","\/\/liveimg.afreecatv.com\/m\/246844816?179","[석사관]-------ㅎㅇ-------\/ 카단 블래스터 로아 성예량","48"],["bbbaesiii","246844912","\/\/liveimg.afreecatv.com\/m\/246844912?34","나사 저그ck 참여 상대 쥬나","43"],["guslgood2","246733853","\/\/liveimg.afreecatv.com\/m\/246733853?629","서든 울산 랜딩 노방종22일차(끝)저녁10시30분에 오겠습니다","42"],["jscando77","246844740","\/\/liveimg.afreecatv.com\/m\/246844740?12","[석사관] 인력석무소 나사 저그ck 몽순님 상대&gt;.&lt;","40"],["gptj000","246844965","\/\/liveimg.afreecatv.com\/m\/246844965?902","\" 혜서 그마 간다 . \"","38"],["by0529","246843543","\/\/liveimg.afreecatv.com\/m\/246843543?811","수뿌 모닝재활래더 S찍기","32"],["pazzy1","246845080","\/\/liveimg.afreecatv.com\/m\/246845080?158","[우끼끼즈] 파찌 화장중","31"],["kalmian","246843924","\/\/liveimg.afreecatv.com\/m\/246843924?367","[석사관] 토스봇 @_@ 안녕하세요 \/\/ 11시 인력사무소!!","23"],["ddd001","246844842","\/\/liveimg.afreecatv.com\/m\/246844842?955","[석사관] 인력사무소!!","21"],["do33ob","246844318","\/\/liveimg.afreecatv.com\/m\/246844318?659","8티어 풀리그 펀딩 귀인 모십니다 ㅇ.ㅇ","21"],["starstim","246843468","\/\/liveimg.afreecatv.com\/m\/246843468?622","스타 테란 탱구화이트 NASA CK 참가","16"],["wpwpwp119","246844648","\/\/liveimg.afreecatv.com\/m\/246844648?140","스타 테란 배지웅 모닝래더ㅎ.ㅎ","14"],["snowssa","246836110","\/\/liveimg.afreecatv.com\/m\/246836110?699","[보신대] 또 24시간.. 4시 기상 깨워 깨우지마 전자녀 10개...  부천스타정중만","14"]],{"캄성":0,"우끼끼즈":2,"바스포드":1,"CP":2,"철와대":0,"NSU":2,"JSA":0,"무친대":1,"아마대":1,"츠나대":2,"MSG":4,"고대학":2}]