[[["vlfvlf789","242373355","\/\/liveimg.afreecatv.com\/m\/242373355?368","MSG ㅈ소대학 다터지는구나..자퇴생발생","2192"],["tladl5572","242370552","\/\/liveimg.afreecatv.com\/m\/242370552?335","NSU 효딤 내가제일잘나가 &gt;.&lt;","1028"],["imhappygood","242373519","\/\/liveimg.afreecatv.com\/m\/242373519?41","괴인협회&gt;스타뉴스&gt;점점 사라지는 대학인원들 또 자퇴생들 발생\/철와대 무친대 바스포드 MSG CP JSA NSU 아마대 우끼끼즈 츠나캄성","887"],["rladuddo99","242365679","\/\/liveimg.afreecatv.com\/m\/242365679?553","[바스포드]스타 구성훈 철권7","367"],["dptmfl1258","242374043","\/\/liveimg.afreecatv.com\/m\/242374043?536","FA 공무원토스 밥소스 갈게요","86"],["dodenvoa","242363034","\/\/liveimg.afreecatv.com\/m\/242363034?58","[JSA] 살려주세요.... 치킨 먹고 싶어요","66"],["laady1","242348720","\/\/liveimg.afreecatv.com\/m\/242348720?974","[바스포드] 연다람지 상윤이 집 다녀오겠슴니다","39"],["eeceec","242373286","\/\/liveimg.afreecatv.com\/m\/242373286?932","[MSG]  7티어 테란 좋은 아침입니다","37"],["lky6407","242373955","\/\/liveimg.afreecatv.com\/m\/242373955?316","[AMA] 아마대 토스 아마토스원탑","27"],["qhkrwns12","242373172","\/\/liveimg.afreecatv.com\/m\/242373172?374","스타 토스 미동미동 진지한래더게임 밤낮바꾸기 LMAO","20"],["bumsoo552","242372867","\/\/liveimg.afreecatv.com\/m\/242372867?296","JSA 스타 김범수 트슈 보라 마꼬 범수 치킨 ㅁ","16"],["jhyhlli123","242373832","\/\/liveimg.afreecatv.com\/m\/242373832?228","[MSG]교수 위메이드 전프로 ","16"],["ppeue0625","242373389","\/\/liveimg.afreecatv.com\/m\/242373389?484","[MSG] 모닝코로나 2일차","14"],["heksd","242373034","\/\/liveimg.afreecatv.com\/m\/242373034?50","[MSG] 파저씨","14"],["alswnghd1","242372314","\/\/liveimg.afreecatv.com\/m\/242372314?868","[MSG &amp; 굿엔터] 오렌지 스타 매칭이 잡혀야 뭘하지 ㅡㅡ","11"],["hy4985","242365099","\/\/liveimg.afreecatv.com\/m\/242365099?789","cp  옆집뽀누나스 타  래더   다른종족 체험중","4"],["ddd001","242374220","\/\/liveimg.afreecatv.com\/m\/242374220?900","MSG) 일주일이 벌써 반이나 지나버렸네 ㅠㅠ","1"],["pookygamja","242373664","\/\/liveimg.afreecatv.com\/m\/242373664?940","뮤비촬영현장","862"],["kisss2","242373354","\/\/liveimg.afreecatv.com\/m\/242373354?17","모닝 운세테스트 브루마블 142개 주사위 던져볼래요? 방셀\/역팬\/한방카톡,식데","78"],["phh95426","242345657","\/\/liveimg.afreecatv.com\/m\/242345657?52","이누야사 틀어놓고 자고옴 372시간노방종 배틀그라운드 팬시참","15"],["chuchu0517","242373413","\/\/liveimg.afreecatv.com\/m\/242373413?270","3일차 신입여캠♥ 청순섹시귀염여캠♥ 1454오늘의상방셀+역팬♥ 룰렛맛집 솜사탕맛집 ","14"],["bigbigjo2","242354913","\/\/liveimg.afreecatv.com\/m\/242354913?320","『이누야샤』\"최초공개\"시청하면 퀵뷰드립니다♥(애니\/만화\/뉴스\/WWE\/나루토\/드래곤볼\/마음의소리\/코난\/검정고무신\/호빵맨\/원피스)","9"],["vlfvlf789","242373355","\/\/liveimg.afreecatv.com\/m\/242373355?558","MSG ㅈ소대학 다터지는구나..자퇴생발생","2192"],["zpdl1313","242370270","\/\/liveimg.afreecatv.com\/m\/242370270?134","케이x수찬x월메x귀요민정 상자깡50만원 배틀그라운드","1662"],["giltae1124","242373337","\/\/liveimg.afreecatv.com\/m\/242373337?233","[생] 파죽의 7연승중 갱제vs초팝원딜러","1512"],["na2un","242366278","\/\/liveimg.afreecatv.com\/m\/242366278?950","NSU 박나닝 사슴배 레이디전 2망개스폰 *^ㅡ^*","1271"],["tladl5572","242370552","\/\/liveimg.afreecatv.com\/m\/242370552?677","NSU 효딤 내가제일잘나가 &gt;.&lt;","1028"],["imhappygood","242373519","\/\/liveimg.afreecatv.com\/m\/242373519?392","괴인협회&gt;스타뉴스&gt;점점 사라지는 대학인원들 또 자퇴생들 발생\/철와대 무친대 바스포드 MSG CP JSA NSU 아마대 우끼끼즈 츠나캄성","887"],["osim0408","242369466","\/\/liveimg.afreecatv.com\/m\/242369466?85","초원 낭비할 감정이 없다. 무감정 솔로랭크","591"],["rladuddo99","242365679","\/\/liveimg.afreecatv.com\/m\/242365679?632","[바스포드]스타 구성훈 철권7","367"],["bora99","242361255","\/\/liveimg.afreecatv.com\/m\/242361255?703","JSA) 10킬 치킨 2000개 \/ 팀3등안에 들시 1000개 무한","129"],["dptmfl1258","242374043","\/\/liveimg.afreecatv.com\/m\/242374043?584","FA 공무원토스 밥소스 갈게요","86"],["ckmin706","242374138","\/\/liveimg.afreecatv.com\/m\/242374138?291","⭐무친대 민찬기⭐ 현시각 미드1황 개인화면 ^^ ","86"],["dodenvoa","242363034","\/\/liveimg.afreecatv.com\/m\/242363034?647","[JSA] 살려주세요.... 치킨 먹고 싶어요","66"],["nanaming4","242364156","\/\/liveimg.afreecatv.com\/m\/242364156?20","[CP] 야무지게 캐리하는 마 우 낭 ^-^","45"],["didi5252","242374186","\/\/liveimg.afreecatv.com\/m\/242374186?202","하이요! 깨달았다..이제 올라갈게 롤토체스\/TFT","42"],["laady1","242348720","\/\/liveimg.afreecatv.com\/m\/242348720?644","[바스포드] 연다람지 상윤이 집 다녀오겠슴니다","39"],["eeceec","242373286","\/\/liveimg.afreecatv.com\/m\/242373286?729","[MSG]  7티어 테란 좋은 아침입니다","37"],["lky6407","242373955","\/\/liveimg.afreecatv.com\/m\/242373955?820","[AMA] 아마대 토스 아마토스원탑","27"],["tjfwkdgks","242372638","\/\/liveimg.afreecatv.com\/m\/242372638?588","라코 멸망전대비 챔프폭 연습겸 챌린저 도전 서폿 챌린저","21"],["qhkrwns12","242373172","\/\/liveimg.afreecatv.com\/m\/242373172?678","스타 토스 미동미동 진지한래더게임 밤낮바꾸기 LMAO","20"],["bumsoo552","242372867","\/\/liveimg.afreecatv.com\/m\/242372867?649","JSA 스타 김범수 트슈 보라 마꼬 범수 치킨 ㅁ","17"],["jhyhlli123","242373832","\/\/liveimg.afreecatv.com\/m\/242373832?664","[MSG]교수 위메이드 전프로 ","16"],["ppeue0625","242373389","\/\/liveimg.afreecatv.com\/m\/242373389?462","[MSG] 모닝코로나 2일차","14"],["heksd","242373034","\/\/liveimg.afreecatv.com\/m\/242373034?669","[MSG] 파저씨","14"],["koo2202","242373595","\/\/liveimg.afreecatv.com\/m\/242373595?318","본이루 좋은아침입니다 저녁합방 많은 관심부탁드립니다","14"],["ywww123","242360881","\/\/liveimg.afreecatv.com\/m\/242360881?820","JSA ) 3부 치킨2000개 미션!@","13"]],{"캄성":0,"우끼끼즈":0,"바스포드":2,"CP":2,"철와대":0,"NSU":2,"JSA":4,"무친대":1,"아마대":1,"츠나대":0,"MSG":7,"FA":0}]