[[["y1026","247545483","\/\/liveimg.afreecatv.com\/m\/247545483?787","철구 철기빵 올오프라인 일요일5시시작 4시기상!잠방","1329"],["wlsrl2566","247555914","\/\/liveimg.afreecatv.com\/m\/247555914?562","NASA 비키니 큰거옵니다 다시보기 X 나사투표 고고","1105"],["subeom12","247555365","\/\/liveimg.afreecatv.com\/m\/247555365?745","스타 라이트클럽 박수범  래더줄빠따 치기","578"],["rnjsgurwls15","247556571","\/\/liveimg.afreecatv.com\/m\/247556571?81","[보신대]스타 권혁진 안녕하세요","215"],["sharpragu","247556121","\/\/liveimg.afreecatv.com\/m\/247556121?294","스타 보신대 조기석 비방연습하러 가기전","126"],["wodnr7872","247554933","\/\/liveimg.afreecatv.com\/m\/247554933?722","[겐세이박] 밥좀먹고할게요 스타 팀플 빨무","94"],["daegalheo","247556155","\/\/liveimg.afreecatv.com\/m\/247556155?111"," 허유 일본라멘 먹방 스타 마이너즈","75"],["rfvtgb778","247554875","\/\/liveimg.afreecatv.com\/m\/247554875?263","스타 이영웅 래더 한번보면 쉽게S가는 쉬운강의 시청자 게임이후 피드백전문^^","62"],["simcheong23","247556537","\/\/liveimg.afreecatv.com\/m\/247556537?35","[보신대] 또봉순  비방합숙하기전~~!   냉면 + 만두 먹방","56"],["soonhani","247556503","\/\/liveimg.afreecatv.com\/m\/247556503?361","[NZU] 늪지대 연도기 대기하면서 본선준비  재활스타 합니다..","55"],["rladuddo99","247555459","\/\/liveimg.afreecatv.com\/m\/247555459?651","구성훈 스타 반갑습니다^^","37"],["luckycontrol","247556880","\/\/liveimg.afreecatv.com\/m\/247556880?723","[YB] 스타 고도준x김무아 제주도 인연 오늘은 될까요..? 서로 요리해주기","31"],["tjr2440","247555037","\/\/liveimg.afreecatv.com\/m\/247555037?817","[스타 프로토스 봉실]","27"],["starstim","247556928","\/\/liveimg.afreecatv.com\/m\/247556928?444","스타 테란 탱구화이트 vs 고니님 7\/4","2"],["ggangsoony","247555643","\/\/liveimg.afreecatv.com\/m\/247555643?613","[MC크루] 장성왔습니다. 맨만숙 날박","363"],["poos69","247548260","\/\/liveimg.afreecatv.com\/m\/247548260?899","[무적단] 농부 도둑 [로나월드 시즌2]","3608"],["didi5252","247497413","\/\/liveimg.afreecatv.com\/m\/247497413?356","중국에서도 와우어메이징을 외친 쪼해피롱식 초가스덱","2014"],["ogm0905","247513680","\/\/liveimg.afreecatv.com\/m\/247513680?7","오뀨  노력의천재  3만개 챌노방종","1915"],["legendhyuk","247555872","\/\/liveimg.afreecatv.com\/m\/247555872?424","오스카 [ 로나월드:시즌2 ] ","1845"],["y1026","247545483","\/\/liveimg.afreecatv.com\/m\/247545483?932","철구 철기빵 올오프라인 일요일5시시작 4시기상!잠방","1342"],["wlsrl2566","247555914","\/\/liveimg.afreecatv.com\/m\/247555914?99","NASA 비키니 큰거옵니다 다시보기 X 나사투표 고고","1101"],["pkdlwpans","247541789","\/\/liveimg.afreecatv.com\/m\/247541789?299","[로나월드 시즌2] 싸패 검은해적단 랄드","778"],["subeom12","247555365","\/\/liveimg.afreecatv.com\/m\/247555365?539","스타 라이트클럽 박수범  래더줄빠따 치기","578"],["tjaudtn123","247554729","\/\/liveimg.afreecatv.com\/m\/247554729?9","서도일 VS 오뀨+초원 숟가락들좀 팰게요","334"],["osim0408","247555617","\/\/liveimg.afreecatv.com\/m\/247555617?858","초원 본캐 1등 달리기 시작","311"],["smmms2002","247555294","\/\/liveimg.afreecatv.com\/m\/247555294?591","[오츠\/로나월드:시즌2]  좋은아침^^","269"],["rnjsgurwls15","247556571","\/\/liveimg.afreecatv.com\/m\/247556571?963","[보신대]스타 권혁진 안녕하세요","207"],["sharpragu","247556121","\/\/liveimg.afreecatv.com\/m\/247556121?138","스타 보신대 조기석 비방연습하러 가기전","126"],["wodnr7872","247554933","\/\/liveimg.afreecatv.com\/m\/247554933?763","[겐세이박] 밥좀먹고할게요 스타 팀플 빨무","90"],["yoomingseo","247555897","\/\/liveimg.afreecatv.com\/m\/247555897?734","[케크루] 유복실","78"],["daegalheo","247556155","\/\/liveimg.afreecatv.com\/m\/247556155?887"," 허유 일본라멘 먹방 스타 마이너즈","75"],["rfvtgb778","247554875","\/\/liveimg.afreecatv.com\/m\/247554875?896","스타 이영웅 래더 한번보면 쉽게S가는 쉬운강의 시청자 게임이후 피드백전문^^","62"],["simcheong23","247556537","\/\/liveimg.afreecatv.com\/m\/247556537?332","[보신대] 또봉순  비방합숙하기전~~!   냉면 + 만두 먹방","56"],["soonhani","247556503","\/\/liveimg.afreecatv.com\/m\/247556503?487","[NZU] 늪지대 연도기 대기하면서 본선준비  재활스타 합니다..","54"],["raso0601","247555522","\/\/liveimg.afreecatv.com\/m\/247555522?955","한판 이기면 실버2 승급 ^0^","43"],["rladuddo99","247555459","\/\/liveimg.afreecatv.com\/m\/247555459?23","구성훈 스타 반갑습니다^^","37"],["godnjs8482","247547822","\/\/liveimg.afreecatv.com\/m\/247547822?184","[BKG] #킬내기공장 #BJ할배","32"],["luckycontrol","247556880","\/\/liveimg.afreecatv.com\/m\/247556880?421","[YB] 스타 고도준x김무아 제주도 인연 오늘은 될까요..? 서로 요리해주기","31"],["tjr2440","247555037","\/\/liveimg.afreecatv.com\/m\/247555037?529","[스타 프로토스 봉실]","27"],["95yvely","247556709","\/\/liveimg.afreecatv.com\/m\/247556709?139","철기빵 10500표 200up시 냥자세 1000up시 19금의첸","3101"]],{"캄성":1,"우끼끼즈":0,"JSA":0,"보신대":4,"DP":0,"라이트클럽":0,"흑카데미":0,"철기빵":1,"YB":2,"석사관":0,"나사":1,"늪지대":0}]