[[["imhappygood","242467487","\/\/liveimg.afreecatv.com\/m\/242467487?937","괴인협회&gt;스타렉카&gt;아무것도 얻을거 없는 이싸움의 끝은? \/철와대 무친대 바스포드 MSG NSU CP JSA 아마대 츠나 캄성 우끼끼즈 ","1324"],["arinbbidol","242467782","\/\/liveimg.afreecatv.com\/m\/242467782?633","기뉴다 스타 마이너즈vs난수 사비에르난데스 쇼타임 짭호 인민재판","724"],["tjdeosks","242463200","\/\/liveimg.afreecatv.com\/m\/242463200?212","스타 저그 김성대","657"],["tladl5572","242458429","\/\/liveimg.afreecatv.com\/m\/242458429?588","NSU 효딤 ","457"],["rhf104","242466989","\/\/liveimg.afreecatv.com\/m\/242466989?926","[캄성여대] 맥모닝팟 풍뎅 러아 석길 런런","295"],["onlysibar","242467648","\/\/liveimg.afreecatv.com\/m\/242467648?325","무친대 스타 샤이니 테란 레더 죠옷나 쉽게올리는 강의","143"],["mhn04149","242466571","\/\/liveimg.afreecatv.com\/m\/242466571?71","우끼끼즈 지니상사 경식 FA","124"],["wkddudrms15","242467694","\/\/liveimg.afreecatv.com\/m\/242467694?460","[아마대] 마이너즈 난수 vs 기뉴다 사비먹고시작하자","75"],["rnjsgurwls15","242467738","\/\/liveimg.afreecatv.com\/m\/242467738?745","CP 스타 권혁진 마이너즈 쇼타임","13"],["skarbwhgc","242466843","\/\/liveimg.afreecatv.com\/m\/242466843?369","[FA] 스타 테란 팔레트 0티어 래더","6"],["gjgj3274","242467840","\/\/liveimg.afreecatv.com\/m\/242467840?121","마이너즈 이소룡 스타 방긋슴다~~!","1"],["vlfvlf789","242467292","\/\/liveimg.afreecatv.com\/m\/242467292?384","MSG 하 진짜 난리났구만..","867"],["dmsgkdn12","242378083","\/\/liveimg.afreecatv.com\/m\/242378083?203","[신입여캠] 돌핀코인타실분 &gt;&lt;♥♥♥","71"],["laady1","242396321","\/\/liveimg.afreecatv.com\/m\/242396321?365","[바스포드] 연다람지 12시 기상,, 1시에 올게요 드디어 120시간 끝이다","16"],["chuchu0517","242467386","\/\/liveimg.afreecatv.com\/m\/242467386?253","7일차 신입여캠♥ 안녕? 좋은아침♥ 1454오늘의상정성방셀+역팬♥ 룰렛맛집 솜사탕맛집","10"],["rrvv17","242464938","\/\/liveimg.afreecatv.com\/m\/242464938?252","킴성태 구적단vs겜창즈 생일감사합니다 24시간불싸지를꼐요 ","8035"],["na2un","242461966","\/\/liveimg.afreecatv.com\/m\/242461966?815","NSU 박나닝 겜창즈 VS 똥적단 현재 1:1 막판 만개빵 ^ㅡ^","1539"],["imhappygood","242467487","\/\/liveimg.afreecatv.com\/m\/242467487?850","괴인협회&gt;스타렉카&gt;아무것도 얻을거 없는 이싸움의 끝은? \/철와대 무친대 바스포드 MSG NSU CP JSA 아마대 츠나 캄성 우끼끼즈 ","1324"],["giltae1124","242466829","\/\/liveimg.afreecatv.com\/m\/242466829?659","[Gou] 갱크스 캐리시200개","777"],["arinbbidol","242467782","\/\/liveimg.afreecatv.com\/m\/242467782?603","기뉴다 스타 마이너즈vs난수 사비에르난데스 쇼타임 짭호 인민재판","736"],["tjdeosks","242463200","\/\/liveimg.afreecatv.com\/m\/242463200?124","스타 저그 김성대","657"],["tladl5572","242458429","\/\/liveimg.afreecatv.com\/m\/242458429?969","NSU 효딤 ","457"],["wnstn0905","242466608","\/\/liveimg.afreecatv.com\/m\/242466608?467","박사장 배틀그라운드 새벽야심한밤에왔습니다 오늘은 ","385"],["rhf104","242466989","\/\/liveimg.afreecatv.com\/m\/242466989?78","[캄성여대] 맥모닝팟 풍뎅 러아 석길 런런","295"],["pkdlwpans","242466621","\/\/liveimg.afreecatv.com\/m\/242466621?267","배틀그라운드 GKL 싸패x킴성태x박사장x써기 vs 나닝x혜원x연진x복희","213"],["onlysibar","242467648","\/\/liveimg.afreecatv.com\/m\/242467648?756","무친대 스타 샤이니 테란 레더 죠옷나 쉽게올리는 강의","143"],["mhn04149","242466571","\/\/liveimg.afreecatv.com\/m\/242466571?891","우끼끼즈 지니상사 경식 FA","125"],["wkddudrms15","242467694","\/\/liveimg.afreecatv.com\/m\/242467694?649","[아마대] 마이너즈 난수 vs 기뉴다 사비먹고시작하자","75"],["jinhi1004","242464996","\/\/liveimg.afreecatv.com\/m\/242464996?778","실버2 원딜러 골드ㅏ 언제가징 ㅠㅠㅠㅠㅠㅠ","31"],["phh95426","242430516","\/\/liveimg.afreecatv.com\/m\/242430516?345","여캠 괴협 갈 준비중 #킬룰렛 444시간노방종 배틀그라운드 배그","25"]],{"캄성":2,"우끼끼즈":1,"바스포드":3,"CP":1,"철와대":1,"NSU":2,"JSA":0,"무친대":1,"아마대":1,"츠나대":0,"MSG":1,"꼰대학":1}]