[[["love1uu","243531791","\/\/liveimg.afreecatv.com\/m\/243531791?293","[철와대]혜미x꿀몬 VS 봉준x성태 사비5000개빵","1621"],["firebathero","243528710","\/\/liveimg.afreecatv.com\/m\/243528710?622","NSU 흑운장 스타 메우ㄴ디 한번에 여러판 하기 작업장 [폐관수련] ","696"],["msuk2017","243523702","\/\/liveimg.afreecatv.com\/m\/243523702?168","메운디 김봉준*킴성태 vs 유혜미*모꿀몬 이마니의 복수","503"],["na2un","243532302","\/\/liveimg.afreecatv.com\/m\/243532302?990","NSU 시1발","234"],["yunhee1222","243531522","\/\/liveimg.afreecatv.com\/m\/243531522?546","[철와대] 예솔 2주년 중요한건 꺾이지 않는 마음.","206"],["skygkrtn","243522796","\/\/liveimg.afreecatv.com\/m\/243522796?685","NSU 메운디 14시간째 에픽 하나 ","201"],["kkmkhh1234","243532396","\/\/liveimg.afreecatv.com\/m\/243532396?979","스타 깨모다 김경모 하위연 ^^","140"],["daeun0793","243523516","\/\/liveimg.afreecatv.com\/m\/243523516?244","NSU 단잉 론멜bj 자러감 시간공지함","83"],["rkdakstlr911","243520124","\/\/liveimg.afreecatv.com\/m\/243520124?799","강만식 메운디CK 첫경험..1일차 태초2번떴습니다..도와주세요","77"],["kmj05317","243521869","\/\/liveimg.afreecatv.com\/m\/243521869?770","우리밍X이뀨X나상윤 메운디 ","57"],["bijyu90","243524263","\/\/liveimg.afreecatv.com\/m\/243524263?820"," 스타 NSU 다린 ","39"],["skarbwhgc","243529440","\/\/liveimg.afreecatv.com\/m\/243529440?710","스타 테란 팔레트 0티어 래더","9"],["john06911","243527125","\/\/liveimg.afreecatv.com\/m\/243527125?400","[FA]이완 테란","8"],["khm11903","243530892","\/\/liveimg.afreecatv.com\/m\/243530892?504","봉준 VS 성태 매운디 사비 18000개빵","20306"],["ch1716","243532069","\/\/liveimg.afreecatv.com\/m\/243532069?200","자다깬 최군형","289"],["pi0314","243530855","\/\/liveimg.afreecatv.com\/m\/243530855?187","파이 잠방","138"],["dmsgkdn12","243516053","\/\/liveimg.afreecatv.com\/m\/243516053?861","[신입여캠]  BJ노방종 ","90"],["rrvv17","243531003","\/\/liveimg.afreecatv.com\/m\/243531003?726","킴성태x봉준팀vs모꿀몬x혜미 5000개빵 ","5654"],["love1uu","243531791","\/\/liveimg.afreecatv.com\/m\/243531791?202","[철와대]혜미x꿀몬 VS 봉준x성태 사비5000개빵","1621"],["firebathero","243528710","\/\/liveimg.afreecatv.com\/m\/243528710?469","NSU 흑운장 스타 메우ㄴ디 한번에 여러판 하기 작업장 [폐관수련] ","696"],["sky2713","243522135","\/\/liveimg.afreecatv.com\/m\/243522135?373","상윤x이뀨x우리밍 메운디 새 삶살기 2일차 노방종","627"],["msuk2017","243523702","\/\/liveimg.afreecatv.com\/m\/243523702?102","메운디 김봉준*킴성태 vs 유혜미*모꿀몬 이마니의 복수","503"],["na2un","243532302","\/\/liveimg.afreecatv.com\/m\/243532302?94","NSU 시1발","235"],["yunhee1222","243531522","\/\/liveimg.afreecatv.com\/m\/243531522?724","[철와대] 예솔 2주년 중요한건 꺾이지 않는 마음.","206"],["skygkrtn","243522796","\/\/liveimg.afreecatv.com\/m\/243522796?952","NSU 메운디 14시간째 에픽 하나 ","201"],["ogm0905","243532318","\/\/liveimg.afreecatv.com\/m\/243532318?873","오뀨 신입 롤비입니다 ㅎㅎ챌까지 ^^ LOL","177"],["kkmkhh1234","243532396","\/\/liveimg.afreecatv.com\/m\/243532396?981","스타 깨모다 김경모 하위연 ^^","140"],["daeun0793","243523516","\/\/liveimg.afreecatv.com\/m\/243523516?878","NSU 단잉 론멜bj 자러감 시간공지함","82"],["rkdakstlr911","243520124","\/\/liveimg.afreecatv.com\/m\/243520124?439","강만식 메운디CK 첫경험..1일차 태초2번떴습니다..도와주세요","77"],["kmj05317","243521869","\/\/liveimg.afreecatv.com\/m\/243521869?159","우리밍X이뀨X나상윤 메운디 ","57"],["pkdlwpans","243519299","\/\/liveimg.afreecatv.com\/m\/243519299?958","배틀그라운드 GKL 싸패 매운디","40"],["bijyu90","243524263","\/\/liveimg.afreecatv.com\/m\/243524263?231"," 스타 NSU 다린 ","39"],["jinhi1004","243521148","\/\/liveimg.afreecatv.com\/m\/243521148?153","실버2 원딜 솔랭 시즌말 달리기","33"],["whddnr2813","243526048","\/\/liveimg.afreecatv.com\/m\/243526048?529","맛종욱 메운디 켠왕 갑니돠 배틀그라운드 ","28"],["godnjs8482","243525031","\/\/liveimg.afreecatv.com\/m\/243525031?778","[BKG]3부 공장 롤체랜드 #BJ할배 #킬내기공장","22"],["jc1507","243532415","\/\/liveimg.afreecatv.com\/m\/243532415?817","NBA 결장자정보 최종본 11월10일 NBA 분석 !! 스포츠분석의 모든것 !!!           ","843"]],{"캄성":0,"우끼끼즈":0,"바스포드":0,"CP":0,"철와대":4,"NSU":5,"JSA":1,"무친대":3,"아마대":0,"츠나대":0,"MSG":0,"고대학":0}]